karrio/mappers/zoom2u/__init__.py
karrio/mappers/zoom2u/mapper.py
karrio/mappers/zoom2u/proxy.py
karrio/mappers/zoom2u/settings.py
karrio/plugins/zoom2u/__init__.py
karrio/providers/zoom2u/__init__.py
karrio/providers/zoom2u/error.py
karrio/providers/zoom2u/rate.py
karrio/providers/zoom2u/tracking.py
karrio/providers/zoom2u/units.py
karrio/providers/zoom2u/utils.py
karrio/providers/zoom2u/shipment/__init__.py
karrio/providers/zoom2u/shipment/cancel.py
karrio/providers/zoom2u/shipment/create.py
karrio/schemas/zoom2u/__init__.py
karrio/schemas/zoom2u/error_response.py
karrio/schemas/zoom2u/rate_request.py
karrio/schemas/zoom2u/rate_response.py
karrio/schemas/zoom2u/shipping_request.py
karrio/schemas/zoom2u/shipping_response.py
karrio/schemas/zoom2u/tracking_response.py
karrio_zoom2u-2026.1.4.dist-info/METADATA
karrio_zoom2u-2026.1.4.dist-info/WHEEL
karrio_zoom2u-2026.1.4.dist-info/entry_points.txt
karrio_zoom2u-2026.1.4.dist-info/top_level.txt
karrio_zoom2u-2026.1.4.dist-info/RECORD
